DELICENSE.txt
LICENSE
MANIFEST.in
README.md
setup.py
user_agent_middleware/__init__.py
user_agent_middleware/admin.py
user_agent_middleware/apps.py
user_agent_middleware/mixims.py
user_agent_middleware/models.py
user_agent_middleware/tests.py
user_agent_middleware/utils.py
user_agent_middleware/views.py
user_agent_middleware.egg-info/PKG-INFO
user_agent_middleware.egg-info/SOURCES.txt
user_agent_middleware.egg-info/dependency_links.txt
user_agent_middleware.egg-info/not-zip-safe
user_agent_middleware.egg-info/requires.txt
user_agent_middleware.egg-info/top_level.txt
user_agent_middleware/middleware/__init__.py
user_agent_middleware/middleware/get_user_agent_info.py
user_agent_middleware/migrations/0001_initial.py
user_agent_middleware/migrations/__init__.py